quartermaster_client/__init__.py
quartermaster_client/__main__.py
quartermaster_client/client/__init__.py
quartermaster_client/client/app.py
quartermaster_client/client/integration/TeamCity.py
quartermaster_client/client/integration/__init__.py
usb_quartermaster_client-0.1.1.dist-info/entry_points.txt
usb_quartermaster_client-0.1.1.dist-info/WHEEL
usb_quartermaster_client-0.1.1.dist-info/METADATA
usb_quartermaster_client-0.1.1.dist-info/RECORD
