Metadata-Version: 2.1
Name: usb-quartermaster-client
Version: 0.1.1
Summary: Client to connect USB devices managed by Quartermaster Server
Author: Tim Laurence
Author-email: timdaman@gmail.com
Requires-Python: >=3.7,<4.0
Classifier: Programming Language :: Python :: 3
Classifier: Programming Language :: Python :: 3.7
Classifier: Programming Language :: Python :: 3.8
Requires-Dist: usb-quartermaster-common (>=0.1.0,<0.2.0)
